{
  "lastRefresh": "2026-04-15T16:59:29.106Z",
  "periodDays": 14,
  "totalFailures": 0,
  "totalPRs": 10,
  "confirmedFlakyCount": 0,
  "mergedDespiteFailureCount": 0,
  "failedTests": [],
  "summary": {
    "totalFailedTests": 0,
    "confirmedFlaky": 0,
    "mergedDespiteFailure": 0,
    "mostAffectedJob": null,
    "trend": [
      {
        "date": "2026-04-02",
        "failures": 0
      },
      {
        "date": "2026-04-03",
        "failures": 0
      },
      {
        "date": "2026-04-04",
        "failures": 0
      },
      {
        "date": "2026-04-05",
        "failures": 0
      },
      {
        "date": "2026-04-06",
        "failures": 0
      },
      {
        "date": "2026-04-07",
        "failures": 0
      },
      {
        "date": "2026-04-08",
        "failures": 0
      },
      {
        "date": "2026-04-09",
        "failures": 0
      },
      {
        "date": "2026-04-10",
        "failures": 0
      },
      {
        "date": "2026-04-11",
        "failures": 0
      },
      {
        "date": "2026-04-12",
        "failures": 0
      },
      {
        "date": "2026-04-13",
        "failures": 0
      },
      {
        "date": "2026-04-14",
        "failures": 0
      },
      {
        "date": "2026-04-15",
        "failures": 0
      }
    ],
    "jobBreakdown": []
  }
}